payload_tagger/__init__.py
payload_tagger/clickup.py
payload_tagger/errors.py
payload_tagger/py.typed
payload_tagger/whatsapp.py
payload_tagger-0.1.3.dist-info/METADATA
payload_tagger-0.1.3.dist-info/WHEEL
payload_tagger-0.1.3.dist-info/licenses/LICENSE
payload_tagger-0.1.3.dist-info/RECORD
